odoo10_addon_account_invoice_pro_forma_sequence-10.0.1.0.0.99.dev5-py3.8-nspkg.pth
odoo/addons/account_invoice_pro_forma_sequence/README.rst
odoo/addons/account_invoice_pro_forma_sequence/__init__.py
odoo/addons/account_invoice_pro_forma_sequence/__manifest__.py
odoo/addons/account_invoice_pro_forma_sequence/i18n/account_invoice_pro_forma_sequence.pot
odoo/addons/account_invoice_pro_forma_sequence/models/__init__.py
odoo/addons/account_invoice_pro_forma_sequence/models/account.py
odoo/addons/account_invoice_pro_forma_sequence/models/account_invoice_settings.py
odoo/addons/account_invoice_pro_forma_sequence/models/company.py
odoo/addons/account_invoice_pro_forma_sequence/readme/CONFIGURE.rst
odoo/addons/account_invoice_pro_forma_sequence/readme/CONTRIBUTORS.rst
odoo/addons/account_invoice_pro_forma_sequence/readme/DESCRIPTION.rst
odoo/addons/account_invoice_pro_forma_sequence/static/description/icon.png
odoo/addons/account_invoice_pro_forma_sequence/static/description/index.html
odoo/addons/account_invoice_pro_forma_sequence/views/account.xml
odoo/addons/account_invoice_pro_forma_sequence/views/account_config_settings.xml
odoo/addons/account_invoice_pro_forma_sequence/views/account_report.xml
odoo10_addon_account_invoice_pro_forma_sequence-10.0.1.0.0.99.dev5.dist-info/METADATA
odoo10_addon_account_invoice_pro_forma_sequence-10.0.1.0.0.99.dev5.dist-info/WHEEL
odoo10_addon_account_invoice_pro_forma_sequence-10.0.1.0.0.99.dev5.dist-info/namespace_packages.txt
odoo10_addon_account_invoice_pro_forma_sequence-10.0.1.0.0.99.dev5.dist-info/top_level.txt
odoo10_addon_account_invoice_pro_forma_sequence-10.0.1.0.0.99.dev5.dist-info/RECORD
