Metadata-Version: 2.1
Name: odoo10-addon-account-invoice-pro-forma-sequence
Version: 10.0.1.0.0.99.dev5
Summary: Bind a sequence to pro-forma invoices
Home-page: https://github.com/OCA/account-invoicing/tree/10.0/account_invoice_pro_forma_sequence
Author: Agile Business Group, Odoo Community Association (OCA)
Author-email: support@odoo-community.org
License: AGPL-3
Platform: UNKNOWN
Classifier: Programming Language :: Python
Classifier: Framework :: Odoo
Classifier: Framework :: Odoo :: 10.0
Classifier: License :: OSI Approved :: GNU Affero General Public License v3
Requires-Python: ~=2.7
Requires-Dist: odoo <10.1dev,>=10.0
